metis_client/__init__.py
metis_client/client.py
metis_client/compat.py
metis_client/const.py
metis_client/exc.py
metis_client/helpers.py
metis_client/metis.py
metis_client/metis_async.py
metis_client/dtos/__init__.py
metis_client/dtos/auth.py
metis_client/dtos/base.py
metis_client/dtos/calculation.py
metis_client/dtos/collection.py
metis_client/dtos/datasource.py
metis_client/dtos/error.py
metis_client/dtos/event.py
metis_client/dtos/resp.py
metis_client/dtos/user.py
metis_client/models/__init__.py
metis_client/models/auth.py
metis_client/models/base.py
metis_client/models/event.py
metis_client/models/hub.py
metis_client/models/subscription.py
metis_client/namespaces/__init__.py
metis_client/namespaces/base.py
metis_client/namespaces/calculations.py
metis_client/namespaces/root.py
metis_client/namespaces/stream.py
metis_client/namespaces/v0.py
metis_client/namespaces/v0_auth.py
metis_client/namespaces/v0_calculations.py
metis_client/namespaces/v0_collections.py
metis_client/namespaces/v0_datasources.py
metis_client-0.7.1.dist-info/LICENSE
metis_client-0.7.1.dist-info/WHEEL
metis_client-0.7.1.dist-info/METADATA
metis_client-0.7.1.dist-info/RECORD
