Metadata-Version: 2.1
Name: metis-client
Version: 0.7.1
Summary: Metis infra API client in Python
Keywords: metis,client
Author-email: Sergei Korolev <knopki@duck.com>
Requires-Python: >=3.8
Classifier: Development Status :: 4 - Beta
Classifier: License :: OSI Approved :: BSD License
Classifier: Intended Audience :: Science/Research
Classifier: Operating System :: OS Independent
Classifier: Programming Language :: Python
Classifier: Programming Language :: Python :: 3
Classifier: Programming Language :: Python :: 3.8
Classifier: Programming Language :: Python :: 3.9
Classifier: Programming Language :: Python :: 3.10
Classifier: Topic :: Scientific/Engineering
Classifier: Topic :: Scientific/Engineering :: Chemistry
Classifier: Topic :: Scientific/Engineering :: Physics
Classifier: Topic :: Scientific/Engineering :: Information Analysis
Requires-Dist: aiohttp >= 3.7.4
Requires-Dist: aiohttp-sse-client >= 0.2.1
Requires-Dist: asgiref >= 3.5.2
Requires-Dist: camel-converter >= 3
Requires-Dist: typing-extensions >= 4.2.0; python_version < '3.11'
Requires-Dist: yarl >= 1.6.3
Requires-Dist: wdb ; extra == "debug"
Requires-Dist: autoflake ; extra == "lint"
Requires-Dist: black >= 24.1 ; extra == "lint"
Requires-Dist: flake8 ; extra == "lint"
Requires-Dist: flake8-bugbear ; extra == "lint"
Requires-Dist: isort ; extra == "lint"
Requires-Dist: mypy >= 1.0.0, <2 ; extra == "lint"
Requires-Dist: pylint ; extra == "lint"
Requires-Dist: pylint-per-file-ignores >= 1 ; extra == "lint"
Requires-Dist: pyupgrade ; extra == "lint"
Requires-Dist: commitizen ; extra == "release"
Requires-Dist: flit ; extra == "release"
Requires-Dist: freezegun ; extra == "test"
Requires-Dist: pytest-aiohttp >= 1.0.4, <2 ; extra == "test"
Requires-Dist: pytest-cov ; extra == "test"
Project-URL: Changelog, https://github.com/tilde-lab/metis-client/blob/master/CHANGELOG.md
Project-URL: Home, https://github.com/tilde-lab/metis-client
Project-URL: Issues, https://github.com/tilde-lab/metis-client/issues
Project-URL: Source, https://github.com/tilde-lab/metis-client
Provides-Extra: debug
Provides-Extra: lint
Provides-Extra: release
Provides-Extra: test
